{"frames": [

{
	"frame": {"x":1,"y":1,"w":288,"h":392}
},
{
	"frame": {"x":1,"y":1,"w":288,"h":392}
},
{
	"frame": {"x":1,"y":1,"w":288,"h":392}
},
{
	"frame": {"x":291,"y":1,"w":288,"h":392}
},
{
	"frame": {"x":581,"y":1,"w":288,"h":392}
},
{
	"frame": {"x":871,"y":1,"w":288,"h":392}
},
{
	"frame": {"x":1161,"y":1,"w":288,"h":392}
},
{
	"frame": {"x":1451,"y":1,"w":288,"h":392}
},
{
	"frame": {"x":1741,"y":1,"w":288,"h":392}
},
{
	"frame": {"x":1,"y":395,"w":288,"h":392}
},
{
	"frame": {"x":291,"y":395,"w":288,"h":392}
},
{
	"frame": {"x":581,"y":395,"w":288,"h":392}
},
{
	"frame": {"x":871,"y":395,"w":288,"h":392}
},
{
	"frame": {"x":1161,"y":395,"w":288,"h":392}
},
{
	"frame": {"x":1451,"y":395,"w":288,"h":392}
},
{
	"frame": {"x":1741,"y":395,"w":288,"h":392}
},
{
	"frame": {"x":1,"y":789,"w":288,"h":392}
},
{
	"frame": {"x":291,"y":789,"w":288,"h":392}
},
{
	"frame": {"x":581,"y":789,"w":288,"h":392}
},
{
	"frame": {"x":871,"y":789,"w":288,"h":392}
},
{
	"frame": {"x":1161,"y":789,"w":288,"h":392}
},
{
	"frame": {"x":1451,"y":789,"w":288,"h":392}
},
{
	"frame": {"x":1741,"y":789,"w":288,"h":392}
},
{
	"frame": {"x":1,"y":1183,"w":288,"h":392}
},
{
	"frame": {"x":291,"y":1183,"w":288,"h":392}
},
{
	"frame": {"x":581,"y":1183,"w":288,"h":392}
},
{
	"frame": {"x":871,"y":1183,"w":288,"h":392}
},
{
	"frame": {"x":1161,"y":1183,"w":288,"h":392}
},
{
	"frame": {"x":1451,"y":1183,"w":288,"h":392}
},
{
	"frame": {"x":1741,"y":1183,"w":288,"h":392}
},
{
	"frame": {"x":1,"y":1577,"w":288,"h":392}
},
{
	"frame": {"x":291,"y":1577,"w":288,"h":392}
},
{
	"frame": {"x":581,"y":1577,"w":288,"h":392}
},
{
	"frame": {"x":871,"y":1577,"w":288,"h":392}
},
{
	"frame": {"x":1161,"y":1577,"w":288,"h":392}
}]
}
